[
    {
        "point_id": "JOMR_nov25_BSD_02_p001",
        "paire_id": "JOMR",
        "player": "RANC Mathilde",
        "action": "serve",
        "grade": "good pass"
    },
    {
        "point_id": "JOMR_nov25_BSD_02_p003",
        "paire_id": "JOMR",
        "player": "OFFREDI Jade",
        "action": "serve",
        "grade": "ace"
    },
    {
        "point_id": "JOMR_nov25_BSD_02_p004",
        "paire_id": "JOMR",
        "player": "OFFREDI Jade",
        "action": "serve",
        "grade": "average pass"
    },
    {
        "point_id": "JOMR_nov25_BSD_02_p005",
        "paire_id": "JOMR",
        "player": "OFFREDI Jade",
        "action": "serve",
        "grade": "undetermined"
    },
    {
        "point_id": "JOMR_nov25_BSD_02_p007",
        "paire_id": "JOMR",
        "player": "RANC Mathilde",
        "action": "serve",
        "grade": "ace"
    },
    {
        "point_id": "JOMR_nov25_BSD_02_p008",
        "paire_id": "JOMR",
        "player": "RANC Mathilde",
        "action": "serve",
        "grade": "ace"
    },
    {
        "point_id": "JOMR_nov25_BSD_02_p009",
        "paire_id": "JOMR",
        "player": "RANC Mathilde",
        "action": "serve",
        "grade": "average pass"
    },
    {
        "point_id": "JOMR_nov25_BSD_02_p011",
        "paire_id": "JOMR",
        "player": "OFFREDI Jade",
        "action": "serve",
        "grade": "ace"
    },
    {
        "point_id": "JOMR_nov25_BSD_02_p012",
        "paire_id": "JOMR",
        "player": "OFFREDI Jade",
        "action": "serve",
        "grade": "good pass"
    },
    {
        "point_id": "JOMR_nov25_BSD_02_p013",
        "paire_id": "JOMR",
        "player": "OFFREDI Jade",
        "action": "serve",
        "grade": "ace"
    },
    {
        "point_id": "JOMR_nov25_BSD_02_p014",
        "paire_id": "JOMR",
        "player": "OFFREDI Jade",
        "action": "serve",
        "grade": "error"
    },
    {
        "point_id": "JOMR_nov25_BSD_02_p016",
        "paire_id": "JOMR",
        "player": "RANC Mathilde",
        "action": "serve",
        "grade": "average pass"
    },
    {
        "point_id": "JOMR_nov25_BSD_02_p018",
        "paire_id": "JOMR",
        "player": "OFFREDI Jade",
        "action": "serve",
        "grade": "average pass"
    },
    {
        "point_id": "JOMR_nov25_BSD_02_p019",
        "paire_id": "JOMR",
        "player": "OFFREDI Jade",
        "action": "serve",
        "grade": "ace"
    },
    {
        "point_id": "JOMR_nov25_BSD_02_p022",
        "paire_id": "JOMR",
        "player": "RANC Mathilde",
        "action": "serve",
        "grade": "average pass"
    },
    {
        "point_id": "JOMR_nov25_BSD_02_p024",
        "paire_id": "JOMR",
        "player": "OFFREDI Jade",
        "action": "serve",
        "grade": "good pass"
    },
    {
        "point_id": "JOMR_nov25_BSD_02_p027",
        "paire_id": "JOMR",
        "player": "RANC Mathilde",
        "action": "serve",
        "grade": "ace"
    },
    {
        "point_id": "JOMR_nov25_BSD_02_p028",
        "paire_id": "JOMR",
        "player": "RANC Mathilde",
        "action": "serve",
        "grade": "ace"
    },
    {
        "point_id": "JOMR_nov25_BSD_02_p029",
        "paire_id": "JOMR",
        "player": "RANC Mathilde",
        "action": "serve",
        "grade": "ace"
    },
    {
        "point_id": "JOMR_nov25_BSD_02_p030",
        "paire_id": "JOMR",
        "player": "RANC Mathilde",
        "action": "serve",
        "grade": "out-of-system pass"
    },
    {
        "point_id": "JOMR_nov25_BSD_02_p031",
        "paire_id": "JOMR",
        "player": "RANC Mathilde",
        "action": "serve",
        "grade": "average pass"
    },
    {
        "point_id": "JOMR_nov25_BSD_02_p033",
        "paire_id": "JOMR",
        "player": "OFFREDI Jade",
        "action": "serve",
        "grade": "out-of-system pass"
    },
    {
        "point_id": "JOMR_nov25_BSD_02_p034",
        "paire_id": "JOMR",
        "player": "OFFREDI Jade",
        "action": "serve",
        "grade": "out-of-system pass"
    },
    {
        "point_id": "JOMR_nov25_BSD_02_p035",
        "paire_id": "JOMR",
        "player": "OFFREDI Jade",
        "action": "serve",
        "grade": "ace"
    },
    {
        "point_id": "JOMR_nov25_BSD_02_p036",
        "paire_id": "JOMR",
        "player": "OFFREDI Jade",
        "action": "serve",
        "grade": "average pass"
    },
    {
        "point_id": "JOMR_nov25_BSD_02_p037",
        "paire_id": "JOMR",
        "player": "OFFREDI Jade",
        "action": "serve",
        "grade": "ace"
    },
    {
        "point_id": "JOMR_nov25_BSD_02_p038",
        "paire_id": "JOMR",
        "player": "OFFREDI Jade",
        "action": "serve",
        "grade": "ace"
    },
    {
        "point_id": "JOMR_nov25_BSD_02_p039",
        "paire_id": "JOMR",
        "player": "OFFREDI Jade",
        "action": "serve",
        "grade": "out-of-system pass"
    }
]